tableone/__init__.py
tableone/deprecations.py
tableone/exceptions.py
tableone/formatting.py
tableone/modality.py
tableone/preprocessors.py
tableone/statistics.py
tableone/tableone.py
tableone/tables.py
tableone/validators.py
tableone-0.9.5.dist-info/METADATA
tableone-0.9.5.dist-info/WHEEL
tableone-0.9.5.dist-info/licenses/LICENSE
tableone-0.9.5.dist-info/RECORD
