Metadata-Version: 2.4
Name: tableone
Version: 0.9.5
Summary: tableone is a package for creating 'Table 1' summary statistics for a patient population.
Project-URL: homepage, https://github.com/tompollard/tableone/
Project-URL: documentation, https://tableone.readthedocs.io/
Project-URL: repository, https://github.com/tompollard/tableone/
Author: Alistair Johnson, Jesse Raffa
Author-email: Tom Pollard <tpollard@mit.edu>
License-Expression: MIT
License-File: LICENSE
Keywords: Table 1,Table one,clinical research,cohort,statistics
Classifier: License :: OSI Approved :: MIT License
Classifier: Operating System :: OS Independent
Classifier: Programming Language :: Python :: 3
Requires-Python: >=3.9
Requires-Dist: jinja2>=3.1.4
Requires-Dist: numpy>=1.19.1
Requires-Dist: openpyxl>=3.1.2
Requires-Dist: pandas>=2.0.3
Requires-Dist: scipy>=1.10.1
Requires-Dist: statsmodels>=0.14.1
Requires-Dist: tabulate>=0.9.0
